jgtfxlive/LiveChartDataExport.py
jgtfxlive/__init__.py
jgtfxlive/config_generator.py
jgtfxlive/common_samples/BatchOrderMonitor.py
jgtfxlive/common_samples/OrderMonitor.py
jgtfxlive/common_samples/OrderMonitorNetting.py
jgtfxlive/common_samples/TableListenerContainer.py
jgtfxlive/common_samples/__init__.py
jgtfxlive/common_samples/common.py
jgtfxlive/ptoLiveChartDataExport/LiveChartDataExport.py
jgtfxlive/ptoLiveChartDataExport/__init__.py
jgtfxlive-0.1.15.dist-info/LICENSE
jgtfxlive-0.1.15.dist-info/METADATA
jgtfxlive-0.1.15.dist-info/WHEEL
jgtfxlive-0.1.15.dist-info/entry_points.txt
jgtfxlive-0.1.15.dist-info/top_level.txt
jgtfxlive-0.1.15.dist-info/RECORD
